terragrunt/__init__.py
terragrunt/s3.py
terragrunt/state.py
terragrunt/terragrunt.py
terragrunt/utils.py
tha_terragrunt-0.1.8.dist-info/LICENSE
tha_terragrunt-0.1.8.dist-info/METADATA
tha_terragrunt-0.1.8.dist-info/WHEEL
tha_terragrunt-0.1.8.dist-info/top_level.txt
tha_terragrunt-0.1.8.dist-info/RECORD
